[
    {
        "Google Processor Name": "IL_Ver_B_Well_Completion",
        "OGRRE Document Type": "Well Completion Report Types B, C, D, E",
        "Page Order Sort": 1.0,
        "Name": "New_Well",
        "Google Data type": "Checkbox",
        "Occurrence": "Optional once",
        "Grouping": "Type of Report",
        "Database Data Type": "bool",
        "Cleaning Function": "clean_bool",
        "Accepted Range": null,
        "Field Specific Notes": null,
        "Model Enabled": "Yes",
        "V1 Fscores": 0.957,
        "V2 Fscores": 0.958,
        "V3 Fscores": 0.964,
        "T1 Fscores": 0.97,
        "T2 Fscores": 0.982,
        "T3 Fscores": 0.958,
        "T4 Fscores": 0.982
    },
    {
        "Google Processor Name": "IL_Ver_B_Well_Completion",
        "OGRRE Document Type": "Well Completion Report Types B, C, D, E",
        "Page Order Sort": 2.0,
        "Name": "Conversion",
        "Google Data type": "Checkbox",
        "Occurrence": "Optional once",
        "Grouping": "Type of Report",
        "Database Data Type": "bool",
        "Cleaning Function": "clean_bool",
        "Accepted Range": null,
        "Field Specific Notes": null,
        "Model Enabled": "Yes",
        "V1 Fscores": 1.0,
        "V2 Fscores": 1.0,
        "V3 Fscores": 1.0,
        "T1 Fscores": 0.969,
        "T2 Fscores": 1.0,
        "T3 Fscores": 1.0,
        "T4 Fscores": 1.0
    },
    {
        "Google Processor Name": "IL_Ver_B_Well_Completion",
        "OGRRE Document Type": "Well Completion Report Types B, C, D, E",
        "Page Order Sort": 3.0,
        "Name": "DOPH",
        "Google Data type": "Checkbox",
        "Occurrence": "Optional once",
        "Grouping": "Type of Report",
        "Database Data Type": "bool",
        "Cleaning Function": "clean_bool",
        "Accepted Range": null,
        "Field Specific Notes": null,
        "Model Enabled": "Yes",
        "V1 Fscores": 1.0,
        "V2 Fscores": 0.994,
        "V3 Fscores": 1.0,
        "T1 Fscores": 0.988,
        "T2 Fscores": 0.994,
        "T3 Fscores": 1.0,
        "T4 Fscores": 1.0
    },
    {
        "Google Processor Name": "IL_Ver_B_Well_Completion",
        "OGRRE Document Type": "Well Completion Report Types B, C, D, E",
        "Page Order Sort": 4.0,
        "Name": "Deepening",
        "Google Data type": "Checkbox",
        "Occurrence": "Optional once",
        "Grouping": "Type of Report",
        "Database Data Type": "bool",
        "Cleaning Function": "clean_bool",
        "Accepted Range": null,
        "Field Specific Notes": null,
        "Model Enabled": "Yes",
        "V1 Fscores": 1.0,
        "V2 Fscores": 1.0,
        "V3 Fscores": 1.0,
        "T1 Fscores": 0.994,
        "T2 Fscores": 0.994,
        "T3 Fscores": 1.0,
        "T4 Fscores": 1.0
    },
    {
        "Google Processor Name": "IL_Ver_B_Well_Completion",
        "OGRRE Document Type": "Well Completion Report Types B, C, D, E",
        "Page Order Sort": 5.0,
        "Name": "Workover",
        "Google Data type": "Checkbox",
        "Occurrence": "Optional once",
        "Grouping": "Type of Report",
        "Database Data Type": "bool",
        "Cleaning Function": "clean_bool",
        "Accepted Range": null,
        "Field Specific Notes": null,
        "Model Enabled": "Yes",
        "V1 Fscores": 0.994,
        "V2 Fscores": 1.0,
        "V3 Fscores": 1.0,
        "T1 Fscores": 0.981,
        "T2 Fscores": 0.969,
        "T3 Fscores": 0.981,
        "T4 Fscores": 0.975
    },
    {
        "Google Processor Name": "IL_Ver_B_Well_Completion",
        "OGRRE Document Type": "Well Completion Report Types B, C, D, E",
        "Page Order Sort": 6.0,
        "Name": "Type_Of_Well_Oil_Producer",
        "Google Data type": "Checkbox",
        "Occurrence": "Optional once",
        "Grouping": "Type of Well",
        "Database Data Type": "bool",
        "Cleaning Function": "clean_bool",
        "Accepted Range": null,
        "Field Specific Notes": null,
        "Model Enabled": "Yes",
        "V1 Fscores": 0.932,
        "V2 Fscores": 0.933,
        "V3 Fscores": 0.933,
        "T1 Fscores": 0.963,
        "T2 Fscores": 0.951,
        "T3 Fscores": 0.908,
        "T4 Fscores": 0.944
    },
    {
        "Google Processor Name": "IL_Ver_B_Well_Completion",
        "OGRRE Document Type": "Well Completion Report Types B, C, D, E",
        "Page Order Sort": 7.0,
        "Name": "Type_Of_Well_Gas_Producer",
        "Google Data type": "Checkbox",
        "Occurrence": "Optional once",
        "Grouping": "Type of Well",
        "Database Data Type": "bool",
        "Cleaning Function": "clean_bool",
        "Accepted Range": null,
        "Field Specific Notes": null,
        "Model Enabled": "Yes",
        "V1 Fscores": 1.0,
        "V2 Fscores": 1.0,
        "V3 Fscores": 1.0,
        "T1 Fscores": 1.0,
        "T2 Fscores": 0.976,
        "T3 Fscores": 1.0,
        "T4 Fscores": 0.994
    },
    {
        "Google Processor Name": "IL_Ver_B_Well_Completion",
        "OGRRE Document Type": "Well Completion Report Types B, C, D, E",
        "Page Order Sort": 8.0,
        "Name": "Type_Of_Well_Class_II_Injection_Well",
        "Google Data type": "Checkbox",
        "Occurrence": "Optional once",
        "Grouping": "Type of Well",
        "Database Data Type": "bool",
        "Cleaning Function": "clean_bool",
        "Accepted Range": null,
        "Field Specific Notes": null,
        "Model Enabled": "Yes",
        "V1 Fscores": 0.982,
        "V2 Fscores": 0.982,
        "V3 Fscores": 0.982,
        "T1 Fscores": 1.0,
        "T2 Fscores": 0.982,
        "T3 Fscores": 0.988,
        "T4 Fscores": 0.988
    },
    {
        "Google Processor Name": "IL_Ver_B_Well_Completion",
        "OGRRE Document Type": "Well Completion Report Types B, C, D, E",
        "Page Order Sort": 9.0,
        "Name": "Type_Of_Well_Water_Supply",
        "Google Data type": "Checkbox",
        "Occurrence": "Optional once",
        "Grouping": "Type of Well",
        "Database Data Type": "bool",
        "Cleaning Function": "clean_bool",
        "Accepted Range": null,
        "Field Specific Notes": null,
        "Model Enabled": "Yes",
        "V1 Fscores": 1.0,
        "V2 Fscores": 1.0,
        "V3 Fscores": 0.994,
        "T1 Fscores": 1.0,
        "T2 Fscores": 0.994,
        "T3 Fscores": 1.0,
        "T4 Fscores": 1.0
    },
    {
        "Google Processor Name": "IL_Ver_B_Well_Completion",
        "OGRRE Document Type": "Well Completion Report Types B, C, D, E",
        "Page Order Sort": 10.0,
        "Name": "Type_Of_Well_Observation",
        "Google Data type": "Checkbox",
        "Occurrence": "Optional once",
        "Grouping": "Type of Well",
        "Database Data Type": "bool",
        "Cleaning Function": "clean_bool",
        "Accepted Range": null,
        "Field Specific Notes": null,
        "Model Enabled": "Yes",
        "V1 Fscores": 1.0,
        "V2 Fscores": 1.0,
        "V3 Fscores": 1.0,
        "T1 Fscores": 1.0,
        "T2 Fscores": 0.994,
        "T3 Fscores": 1.0,
        "T4 Fscores": 1.0
    },
    {
        "Google Processor Name": "IL_Ver_B_Well_Completion",
        "OGRRE Document Type": "Well Completion Report Types B, C, D, E",
        "Page Order Sort": 11.0,
        "Name": "Type_Of_Well_Gas_Storage",
        "Google Data type": "Checkbox",
        "Occurrence": "Optional once",
        "Grouping": "Type of Well",
        "Database Data Type": "bool",
        "Cleaning Function": "clean_bool",
        "Accepted Range": null,
        "Field Specific Notes": null,
        "Model Enabled": "Yes",
        "V1 Fscores": 1.0,
        "V2 Fscores": 1.0,
        "V3 Fscores": 1.0,
        "T1 Fscores": 1.0,
        "T2 Fscores": 0.994,
        "T3 Fscores": 1.0,
        "T4 Fscores": 1.0
    },
    {
        "Google Processor Name": "IL_Ver_B_Well_Completion",
        "OGRRE Document Type": "Well Completion Report Types B, C, D, E",
        "Page Order Sort": 12.0,
        "Name": "Type_Of_Well_D_And_A",
        "Google Data type": "Checkbox",
        "Occurrence": "Optional once",
        "Grouping": "Type of Well",
        "Database Data Type": "bool",
        "Cleaning Function": "clean_bool",
        "Accepted Range": null,
        "Field Specific Notes": null,
        "Model Enabled": "Yes",
        "V1 Fscores": 1.0,
        "V2 Fscores": 1.0,
        "V3 Fscores": 1.0,
        "T1 Fscores": 0.988,
        "T2 Fscores": 0.994,
        "T3 Fscores": 1.0,
        "T4 Fscores": 1.0
    },
    {
        "Google Processor Name": "IL_Ver_B_Well_Completion",
        "OGRRE Document Type": "Well Completion Report Types B, C, D, E",
        "Page Order Sort": 13.0,
        "Name": "Type_Of_Well_Other",
        "Google Data type": "Checkbox",
        "Occurrence": "Optional once",
        "Grouping": "Type of Well",
        "Database Data Type": "bool",
        "Cleaning Function": "clean_bool",
        "Accepted Range": null,
        "Field Specific Notes": null,
        "Model Enabled": "Yes",
        "V1 Fscores": 0.93,
        "V2 Fscores": 0.93,
        "V3 Fscores": 0.93,
        "T1 Fscores": 0.933,
        "T2 Fscores": 0.93,
        "T3 Fscores": 0.93,
        "T4 Fscores": 0.909
    },
    {
        "Google Processor Name": "IL_Ver_B_Well_Completion",
        "OGRRE Document Type": "Well Completion Report Types B, C, D, E",
        "Page Order Sort": 14.0,
        "Name": "Type_Of_Well_Other_Text",
        "Google Data type": "Plain text",
        "Occurrence": "Optional once",
        "Grouping": "Type of Well",
        "Database Data Type": "str",
        "Cleaning Function": null,
        "Accepted Range": "A-z0-9{1,30}",
        "Field Specific Notes": null,
        "Model Enabled": "No",
        "V1 Fscores": null,
        "V2 Fscores": null,
        "V3 Fscores": null,
        "T1 Fscores": null,
        "T2 Fscores": null,
        "T3 Fscores": null,
        "T4 Fscores": null
    },
    {
        "Google Processor Name": "IL_Ver_B_Well_Completion",
        "OGRRE Document Type": "Well Completion Report Types B, C, D, E",
        "Page Order Sort": 15.0,
        "Name": "Type_Of_Well_Service_Well",
        "Google Data type": "Checkbox",
        "Occurrence": "Optional once",
        "Grouping": "Type of Well",
        "Database Data Type": "bool",
        "Cleaning Function": "clean_bool",
        "Accepted Range": null,
        "Field Specific Notes": null,
        "Model Enabled": "Yes",
        "V1 Fscores": 1.0,
        "V2 Fscores": 1.0,
        "V3 Fscores": 1.0,
        "T1 Fscores": 1.0,
        "T2 Fscores": 1.0,
        "T3 Fscores": 1.0,
        "T4 Fscores": 1.0
    },
    {
        "Google Processor Name": "IL_Ver_B_Well_Completion",
        "OGRRE Document Type": "Well Completion Report Types B, C, D, E",
        "Page Order Sort": 16.0,
        "Name": "Type_Of_Well_Service_Well_Text",
        "Google Data type": "Plain text",
        "Occurrence": "Optional once",
        "Grouping": "Type of Well",
        "Database Data Type": "str",
        "Cleaning Function": null,
        "Accepted Range": "A-z0-9{1,30}",
        "Field Specific Notes": null,
        "Model Enabled": "No",
        "V1 Fscores": null,
        "V2 Fscores": null,
        "V3 Fscores": null,
        "T1 Fscores": null,
        "T2 Fscores": null,
        "T3 Fscores": null,
        "T4 Fscores": null
    },
    {
        "Google Processor Name": "IL_Ver_B_Well_Completion",
        "OGRRE Document Type": "Well Completion Report Types B, C, D, E",
        "Page Order Sort": 17.0,
        "Name": "Type_Of_Well_Coal_Bed_Gas",
        "Google Data type": "Checkbox",
        "Occurrence": "Optional once",
        "Grouping": "Type of Well",
        "Database Data Type": "bool",
        "Cleaning Function": "clean_bool",
        "Accepted Range": null,
        "Field Specific Notes": null,
        "Model Enabled": "Yes",
        "V1 Fscores": 1.0,
        "V2 Fscores": 1.0,
        "V3 Fscores": 1.0,
        "T1 Fscores": 1.0,
        "T2 Fscores": 1.0,
        "T3 Fscores": 1.0,
        "T4 Fscores": 1.0
    },
    {
        "Google Processor Name": "IL_Ver_B_Well_Completion",
        "OGRRE Document Type": "Well Completion Report Types B, C, D, E",
        "Page Order Sort": 18.0,
        "Name": "Type_Of_Well_Coal_Mine_Gas",
        "Google Data type": "Checkbox",
        "Occurrence": "Optional once",
        "Grouping": "Type of Well",
        "Database Data Type": "bool",
        "Cleaning Function": "clean_bool",
        "Accepted Range": null,
        "Field Specific Notes": null,
        "Model Enabled": "Yes",
        "V1 Fscores": 1.0,
        "V2 Fscores": 1.0,
        "V3 Fscores": 1.0,
        "T1 Fscores": 1.0,
        "T2 Fscores": 1.0,
        "T3 Fscores": 1.0,
        "T4 Fscores": 1.0
    },
    {
        "Google Processor Name": "IL_Ver_B_Well_Completion",
        "OGRRE Document Type": "Well Completion Report Types B, C, D, E",
        "Page Order Sort": 19.0,
        "Name": "Permittee",
        "Google Data type": "Plain text",
        "Occurrence": "Optional once",
        "Grouping": null,
        "Database Data Type": "str",
        "Cleaning Function": null,
        "Accepted Range": "A-z0-9{1,60}",
        "Field Specific Notes": null,
        "Model Enabled": "Yes",
        "V1 Fscores": 0.882,
        "V2 Fscores": 0.883,
        "V3 Fscores": 0.914,
        "T1 Fscores": 0.928,
        "T2 Fscores": 0.964,
        "T3 Fscores": 0.94,
        "T4 Fscores": 0.928
    },
    {
        "Google Processor Name": "IL_Ver_B_Well_Completion",
        "OGRRE Document Type": "Well Completion Report Types B, C, D, E",
        "Page Order Sort": 20.0,
        "Name": "Permittee_Number",
        "Google Data type": "Plain text",
        "Occurrence": "Optional once",
        "Grouping": null,
        "Database Data Type": "int",
        "Cleaning Function": "string_to_int",
        "Accepted Range": "0-9{1,15}",
        "Field Specific Notes": null,
        "Model Enabled": "Yes",
        "V1 Fscores": 0.825,
        "V2 Fscores": 0.861,
        "V3 Fscores": 0.842,
        "T1 Fscores": 0.886,
        "T2 Fscores": 0.875,
        "T3 Fscores": 0.886,
        "T4 Fscores": 0.857
    },
    {
        "Google Processor Name": "IL_Ver_B_Well_Completion",
        "OGRRE Document Type": "Well Completion Report Types B, C, D, E",
        "Page Order Sort": 21.0,
        "Name": "Well_Name",
        "Google Data type": "Plain text",
        "Occurrence": "Optional once",
        "Grouping": null,
        "Database Data Type": "str",
        "Cleaning Function": null,
        "Accepted Range": "A-z0-9{1,60}",
        "Field Specific Notes": null,
        "Model Enabled": "Yes",
        "V1 Fscores": 0.896,
        "V2 Fscores": 0.908,
        "V3 Fscores": 0.907,
        "T1 Fscores": 0.945,
        "T2 Fscores": 0.909,
        "T3 Fscores": 0.952,
        "T4 Fscores": 0.952
    },
    {
        "Google Processor Name": "IL_Ver_B_Well_Completion",
        "OGRRE Document Type": "Well Completion Report Types B, C, D, E",
        "Page Order Sort": 22.0,
        "Name": "Permit_Number",
        "Google Data type": "Plain text",
        "Occurrence": "Optional once",
        "Grouping": null,
        "Database Data Type": "int",
        "Cleaning Function": "string_to_int",
        "Accepted Range": "0-9{1,15}",
        "Field Specific Notes": null,
        "Model Enabled": "Yes",
        "V1 Fscores": 0.955,
        "V2 Fscores": 0.95,
        "V3 Fscores": 0.988,
        "T1 Fscores": 0.988,
        "T2 Fscores": 0.982,
        "T3 Fscores": 0.976,
        "T4 Fscores": 0.982
    },
    {
        "Google Processor Name": "IL_Ver_B_Well_Completion",
        "OGRRE Document Type": "Well Completion Report Types B, C, D, E",
        "Page Order Sort": 23.0,
        "Name": "Location",
        "Google Data type": "Plain text",
        "Occurrence": "Optional multiple",
        "Grouping": null,
        "Database Data Type": "str",
        "Cleaning Function": null,
        "Accepted Range": null,
        "Field Specific Notes": null,
        "Model Enabled": "Yes",
        "V1 Fscores": 0.831,
        "V2 Fscores": 0.835,
        "V3 Fscores": 0.834,
        "T1 Fscores": 0.952,
        "T2 Fscores": 0.919,
        "T3 Fscores": 0.952,
        "T4 Fscores": 0.964
    },
    {
        "Google Processor Name": "IL_Ver_B_Well_Completion",
        "OGRRE Document Type": "Well Completion Report Types B, C, D, E",
        "Page Order Sort": 24.0,
        "Name": "Reference_Number",
        "Google Data type": "Plain text",
        "Occurrence": "Optional once",
        "Grouping": null,
        "Database Data Type": "int",
        "Cleaning Function": "string_to_int",
        "Accepted Range": "0-9{1,15}",
        "Field Specific Notes": null,
        "Model Enabled": "Yes",
        "V1 Fscores": 0.973,
        "V2 Fscores": 0.96,
        "V3 Fscores": 0.973,
        "T1 Fscores": 0.966,
        "T2 Fscores": 0.973,
        "T3 Fscores": 0.947,
        "T4 Fscores": 0.953
    },
    {
        "Google Processor Name": "IL_Ver_B_Well_Completion",
        "OGRRE Document Type": "Well Completion Report Types B, C, D, E",
        "Page Order Sort": 25.0,
        "Name": "County",
        "Google Data type": "Plain text",
        "Occurrence": "Optional once",
        "Grouping": null,
        "Database Data Type": "str",
        "Cleaning Function": null,
        "Accepted Range": null,
        "Field Specific Notes": "State Counties",
        "Model Enabled": "Yes",
        "V1 Fscores": 0.988,
        "V2 Fscores": 0.994,
        "V3 Fscores": 1.0,
        "T1 Fscores": 1.0,
        "T2 Fscores": 0.994,
        "T3 Fscores": 1.0,
        "T4 Fscores": 1.0
    },
    {
        "Google Processor Name": "IL_Ver_B_Well_Completion",
        "OGRRE Document Type": "Well Completion Report Types B, C, D, E",
        "Page Order Sort": 26.0,
        "Name": "Section",
        "Google Data type": "Plain text",
        "Occurrence": "Optional once",
        "Grouping": null,
        "Database Data Type": "int",
        "Cleaning Function": "string_to_int",
        "Accepted Range": "0-36",
        "Field Specific Notes": null,
        "Model Enabled": "Yes",
        "V1 Fscores": 0.981,
        "V2 Fscores": 0.994,
        "V3 Fscores": 0.963,
        "T1 Fscores": 0.988,
        "T2 Fscores": 0.982,
        "T3 Fscores": 0.976,
        "T4 Fscores": 0.988
    },
    {
        "Google Processor Name": "IL_Ver_B_Well_Completion",
        "OGRRE Document Type": "Well Completion Report Types B, C, D, E",
        "Page Order Sort": 27.0,
        "Name": "Township",
        "Google Data type": "Plain text",
        "Occurrence": "Optional once",
        "Grouping": null,
        "Database Data Type": "str",
        "Cleaning Function": null,
        "Accepted Range": "A-z0-9{1,3}",
        "Field Specific Notes": "{#N,#S,#}, #==int",
        "Model Enabled": "Yes",
        "V1 Fscores": 0.957,
        "V2 Fscores": 0.963,
        "V3 Fscores": 0.957,
        "T1 Fscores": 0.957,
        "T2 Fscores": 0.951,
        "T3 Fscores": 0.928,
        "T4 Fscores": 0.928
    },
    {
        "Google Processor Name": "IL_Ver_B_Well_Completion",
        "OGRRE Document Type": "Well Completion Report Types B, C, D, E",
        "Page Order Sort": 28.0,
        "Name": "Range",
        "Google Data type": "Plain text",
        "Occurrence": "Optional once",
        "Grouping": null,
        "Database Data Type": "str",
        "Cleaning Function": null,
        "Accepted Range": "A-z0-9{1,3}",
        "Field Specific Notes": "{#E,#W,#}, #==int",
        "Model Enabled": "Yes",
        "V1 Fscores": 0.976,
        "V2 Fscores": 0.976,
        "V3 Fscores": 0.976,
        "T1 Fscores": 0.982,
        "T2 Fscores": 0.969,
        "T3 Fscores": 0.988,
        "T4 Fscores": 0.982
    },
    {
        "Google Processor Name": "IL_Ver_B_Well_Completion",
        "OGRRE Document Type": "Well Completion Report Types B, C, D, E",
        "Page Order Sort": 29.0,
        "Name": "Well_Not_Drilled_Converted_Permit_Expired",
        "Google Data type": "Checkbox",
        "Occurrence": "Optional once",
        "Grouping": "Permit Expired",
        "Database Data Type": "bool",
        "Cleaning Function": "clean_bool",
        "Accepted Range": null,
        "Field Specific Notes": null,
        "Model Enabled": "Yes",
        "V1 Fscores": 1.0,
        "V2 Fscores": 1.0,
        "V3 Fscores": 1.0,
        "T1 Fscores": 1.0,
        "T2 Fscores": 1.0,
        "T3 Fscores": 1.0,
        "T4 Fscores": 1.0
    },
    {
        "Google Processor Name": "IL_Ver_B_Well_Completion",
        "OGRRE Document Type": "Well Completion Report Types B, C, D, E",
        "Page Order Sort": 30.0,
        "Name": "Well_Not_Converted_Permit_Expired",
        "Google Data type": "Checkbox",
        "Occurrence": "Optional once",
        "Grouping": "Permit Expired",
        "Database Data Type": "bool",
        "Cleaning Function": "clean_bool",
        "Accepted Range": null,
        "Field Specific Notes": null,
        "Model Enabled": "Yes",
        "V1 Fscores": 1.0,
        "V2 Fscores": 1.0,
        "V3 Fscores": 1.0,
        "T1 Fscores": 1.0,
        "T2 Fscores": 1.0,
        "T3 Fscores": 1.0,
        "T4 Fscores": 1.0
    },
    {
        "Google Processor Name": "IL_Ver_B_Well_Completion",
        "OGRRE Document Type": "Well Completion Report Types B, C, D, E",
        "Page Order Sort": 31.0,
        "Name": "Well_Not_Drilled_Permit_Expired",
        "Google Data type": "Checkbox",
        "Occurrence": "Optional once",
        "Grouping": "Permit Expired",
        "Database Data Type": "bool",
        "Cleaning Function": "clean_bool",
        "Accepted Range": null,
        "Field Specific Notes": null,
        "Model Enabled": "Yes",
        "V1 Fscores": 1.0,
        "V2 Fscores": 1.0,
        "V3 Fscores": 0.99,
        "T1 Fscores": 1.0,
        "T2 Fscores": 1.0,
        "T3 Fscores": 1.0,
        "T4 Fscores": 1.0
    },
    {
        "Google Processor Name": "IL_Ver_B_Well_Completion",
        "OGRRE Document Type": "Well Completion Report Types B, C, D, E",
        "Page Order Sort": 32.0,
        "Name": "Date_Drilling_Began",
        "Google Data type": "Datetime",
        "Occurrence": "Optional once",
        "Grouping": null,
        "Database Data Type": "date",
        "Cleaning Function": "clean_date",
        "Accepted Range": null,
        "Field Specific Notes": null,
        "Model Enabled": "Yes",
        "V1 Fscores": 0.941,
        "V2 Fscores": 0.981,
        "V3 Fscores": 0.972,
        "T1 Fscores": 0.981,
        "T2 Fscores": 1.0,
        "T3 Fscores": 0.991,
        "T4 Fscores": 0.991
    },
    {
        "Google Processor Name": "IL_Ver_B_Well_Completion",
        "OGRRE Document Type": "Well Completion Report Types B, C, D, E",
        "Page Order Sort": 33.0,
        "Name": "Date_Drilling_Finished",
        "Google Data type": "Datetime",
        "Occurrence": "Optional once",
        "Grouping": null,
        "Database Data Type": "date",
        "Cleaning Function": "clean_date",
        "Accepted Range": null,
        "Field Specific Notes": null,
        "Model Enabled": "Yes",
        "V1 Fscores": 0.898,
        "V2 Fscores": 0.918,
        "V3 Fscores": 0.961,
        "T1 Fscores": 0.981,
        "T2 Fscores": 0.99,
        "T3 Fscores": 0.962,
        "T4 Fscores": 0.981
    },
    {
        "Google Processor Name": "IL_Ver_B_Well_Completion",
        "OGRRE Document Type": "Well Completion Report Types B, C, D, E",
        "Page Order Sort": 34.0,
        "Name": "Elevation_KB",
        "Google Data type": "Plain text",
        "Occurrence": "Optional once",
        "Grouping": null,
        "Database Data Type": "float",
        "Cleaning Function": "string_to_float",
        "Accepted Range": "0-1000",
        "Field Specific Notes": null,
        "Model Enabled": "Yes",
        "V1 Fscores": 0.969,
        "V2 Fscores": 0.898,
        "V3 Fscores": 0.959,
        "T1 Fscores": 1.0,
        "T2 Fscores": 0.97,
        "T3 Fscores": 0.95,
        "T4 Fscores": 0.918
    },
    {
        "Google Processor Name": "IL_Ver_B_Well_Completion",
        "OGRRE Document Type": "Well Completion Report Types B, C, D, E",
        "Page Order Sort": 35.0,
        "Name": "Elevation_DF",
        "Google Data type": "Plain text",
        "Occurrence": "Optional once",
        "Grouping": null,
        "Database Data Type": "float",
        "Cleaning Function": "string_to_float",
        "Accepted Range": "0-1000",
        "Field Specific Notes": null,
        "Model Enabled": "Yes",
        "V1 Fscores": 0.957,
        "V2 Fscores": 0.737,
        "V3 Fscores": 0.737,
        "T1 Fscores": 0.884,
        "T2 Fscores": 0.894,
        "T3 Fscores": 0.894,
        "T4 Fscores": 0.863
    },
    {
        "Google Processor Name": "IL_Ver_B_Well_Completion",
        "OGRRE Document Type": "Well Completion Report Types B, C, D, E",
        "Page Order Sort": 36.0,
        "Name": "Elevation_GR",
        "Google Data type": "Plain text",
        "Occurrence": "Optional once",
        "Grouping": null,
        "Database Data Type": "float",
        "Cleaning Function": "string_to_float",
        "Accepted Range": "0-1000",
        "Field Specific Notes": null,
        "Model Enabled": "Yes",
        "V1 Fscores": 0.958,
        "V2 Fscores": 0.959,
        "V3 Fscores": 0.896,
        "T1 Fscores": 0.969,
        "T2 Fscores": 0.969,
        "T3 Fscores": 0.98,
        "T4 Fscores": 0.969
    },
    {
        "Google Processor Name": "IL_Ver_B_Well_Completion",
        "OGRRE Document Type": "Well Completion Report Types B, C, D, E",
        "Page Order Sort": 37.0,
        "Name": "Rotary_From",
        "Google Data type": "Plain text",
        "Occurrence": "Optional once",
        "Grouping": null,
        "Database Data Type": "float",
        "Cleaning Function": "string_to_float",
        "Accepted Range": "0-20000",
        "Field Specific Notes": "{#, TD, Total Depth, Surface}, #==Float, TD and Total Depth ==Total_Depth, Surface==0.0",
        "Model Enabled": "Yes",
        "V1 Fscores": 0.977,
        "V2 Fscores": 0.989,
        "V3 Fscores": 0.989,
        "T1 Fscores": 0.956,
        "T2 Fscores": 0.921,
        "T3 Fscores": 0.909,
        "T4 Fscores": 0.966
    },
    {
        "Google Processor Name": "IL_Ver_B_Well_Completion",
        "OGRRE Document Type": "Well Completion Report Types B, C, D, E",
        "Page Order Sort": 38.0,
        "Name": "Rotary_To",
        "Google Data type": "Plain text",
        "Occurrence": "Optional once",
        "Grouping": null,
        "Database Data Type": "float",
        "Cleaning Function": "string_to_float",
        "Accepted Range": "0-20000",
        "Field Specific Notes": "{#, TD, Total Depth, Surface}, #==Float, TD and Total Depth ==Total_Depth, Surface==0.0",
        "Model Enabled": "Yes",
        "V1 Fscores": 0.876,
        "V2 Fscores": 0.946,
        "V3 Fscores": 0.938,
        "T1 Fscores": 0.936,
        "T2 Fscores": 0.913,
        "T3 Fscores": 0.872,
        "T4 Fscores": 0.903
    },
    {
        "Google Processor Name": "IL_Ver_B_Well_Completion",
        "OGRRE Document Type": "Well Completion Report Types B, C, D, E",
        "Page Order Sort": 39.0,
        "Name": "Cable_From",
        "Google Data type": "Plain text",
        "Occurrence": "Optional once",
        "Grouping": null,
        "Database Data Type": "float",
        "Cleaning Function": "string_to_float",
        "Accepted Range": "0-20000",
        "Field Specific Notes": "{#, TD, Total Depth, Surface}, #==Float, TD and Total Depth ==Total_Depth, Surface==0.0",
        "Model Enabled": "No",
        "V1 Fscores": null,
        "V2 Fscores": null,
        "V3 Fscores": null,
        "T1 Fscores": null,
        "T2 Fscores": null,
        "T3 Fscores": null,
        "T4 Fscores": null
    },
    {
        "Google Processor Name": "IL_Ver_B_Well_Completion",
        "OGRRE Document Type": "Well Completion Report Types B, C, D, E",
        "Page Order Sort": 40.0,
        "Name": "Cable_To",
        "Google Data type": "Plain text",
        "Occurrence": "Optional once",
        "Grouping": null,
        "Database Data Type": "float",
        "Cleaning Function": "string_to_float",
        "Accepted Range": "0-20000",
        "Field Specific Notes": "{#, TD, Total Depth, Surface}, #==Float, TD and Total Depth ==Total_Depth, Surface==0.0",
        "Model Enabled": "No",
        "V1 Fscores": null,
        "V2 Fscores": null,
        "V3 Fscores": null,
        "T1 Fscores": null,
        "T2 Fscores": null,
        "T3 Fscores": null,
        "T4 Fscores": null
    },
    {
        "Google Processor Name": "IL_Ver_B_Well_Completion",
        "OGRRE Document Type": "Well Completion Report Types B, C, D, E",
        "Page Order Sort": 41.0,
        "Name": "Total_Depth",
        "Google Data type": "Plain text",
        "Occurrence": "Optional once",
        "Grouping": null,
        "Database Data Type": "float",
        "Cleaning Function": "string_to_float",
        "Accepted Range": "0-20000",
        "Field Specific Notes": null,
        "Model Enabled": "Yes",
        "V1 Fscores": 0.99,
        "V2 Fscores": 0.99,
        "V3 Fscores": 0.905,
        "T1 Fscores": 1.0,
        "T2 Fscores": 0.99,
        "T3 Fscores": 0.99,
        "T4 Fscores": 0.99
    },
    {
        "Google Processor Name": "IL_Ver_B_Well_Completion",
        "OGRRE Document Type": "Well Completion Report Types B, C, D, E",
        "Page Order Sort": 42.0,
        "Name": "PBTD",
        "Google Data type": "Plain text",
        "Occurrence": "Optional once",
        "Grouping": null,
        "Database Data Type": "float",
        "Cleaning Function": "string_to_float",
        "Accepted Range": "0-20000",
        "Field Specific Notes": "{#, TD, Total Depth, Surface}, #==Float, TD and Total Depth ==Total_Depth, Surface==0.0",
        "Model Enabled": "Yes",
        "V1 Fscores": 0.692,
        "V2 Fscores": 0.769,
        "V3 Fscores": 0.857,
        "T1 Fscores": 0.909,
        "T2 Fscores": 0.903,
        "T3 Fscores": 0.8,
        "T4 Fscores": 0.824
    },
    {
        "Google Processor Name": "IL_Ver_B_Well_Completion",
        "OGRRE Document Type": "Well Completion Report Types B, C, D, E",
        "Page Order Sort": 43.0,
        "Name": "Wireline_Logs_Run_Yes",
        "Google Data type": "Checkbox",
        "Occurrence": "Optional once",
        "Grouping": "Wireline Logs Run",
        "Database Data Type": "bool",
        "Cleaning Function": "clean_bool",
        "Accepted Range": null,
        "Field Specific Notes": null,
        "Model Enabled": "Yes",
        "V1 Fscores": 0.712,
        "V2 Fscores": 0.724,
        "V3 Fscores": 0.697,
        "T1 Fscores": 0.68,
        "T2 Fscores": 0.674,
        "T3 Fscores": 0.667,
        "T4 Fscores": 0.679
    },
    {
        "Google Processor Name": "IL_Ver_B_Well_Completion",
        "OGRRE Document Type": "Well Completion Report Types B, C, D, E",
        "Page Order Sort": 44.0,
        "Name": "Wireline_Logs_Run_No",
        "Google Data type": "Checkbox",
        "Occurrence": "Optional once",
        "Grouping": "Wireline Logs Run",
        "Database Data Type": "bool",
        "Cleaning Function": "clean_bool",
        "Accepted Range": null,
        "Field Specific Notes": null,
        "Model Enabled": "Yes",
        "V1 Fscores": 0.635,
        "V2 Fscores": 0.605,
        "V3 Fscores": 0.621,
        "T1 Fscores": 0.636,
        "T2 Fscores": 0.636,
        "T3 Fscores": 0.578,
        "T4 Fscores": 0.636
    },
    {
        "Google Processor Name": "IL_Ver_B_Well_Completion",
        "OGRRE Document Type": "Well Completion Report Types B, C, D, E",
        "Page Order Sort": 45.0,
        "Name": "Type_Of_Logs",
        "Google Data type": "Parent",
        "Occurrence": "Optional multiple",
        "Grouping": null,
        "Database Data Type": "Table",
        "Cleaning Function": null,
        "Accepted Range": null,
        "Field Specific Notes": null,
        "Model Enabled": "Yes",
        "V1 Fscores": null,
        "V2 Fscores": null,
        "V3 Fscores": 0.914,
        "T1 Fscores": null,
        "T2 Fscores": null,
        "T3 Fscores": 0.976,
        "T4 Fscores": 0.954
    },
    {
        "Google Processor Name": "IL_Ver_B_Well_Completion",
        "OGRRE Document Type": "Well Completion Report Types B, C, D, E",
        "Page Order Sort": 46.0,
        "Name": "Type_Of_Logs:Type_Of_Log",
        "Google Data type": "Plain text",
        "Occurrence": "Optional once",
        "Grouping": null,
        "Database Data Type": "str",
        "Cleaning Function": null,
        "Accepted Range": "A-z0-9{1,60}",
        "Field Specific Notes": null,
        "Model Enabled": "Yes",
        "V1 Fscores": null,
        "V2 Fscores": null,
        "V3 Fscores": 0.862,
        "T1 Fscores": null,
        "T2 Fscores": null,
        "T3 Fscores": 0.958,
        "T4 Fscores": 0.931
    },
    {
        "Google Processor Name": "IL_Ver_B_Well_Completion",
        "OGRRE Document Type": "Well Completion Report Types B, C, D, E",
        "Page Order Sort": 47.0,
        "Name": "Type_Of_Logs::Date",
        "Google Data type": "Datetime",
        "Occurrence": "Optional once",
        "Grouping": null,
        "Database Data Type": "date",
        "Cleaning Function": "clean_date",
        "Accepted Range": null,
        "Field Specific Notes": null,
        "Model Enabled": "Yes",
        "V1 Fscores": null,
        "V2 Fscores": null,
        "V3 Fscores": 0.973,
        "T1 Fscores": null,
        "T2 Fscores": null,
        "T3 Fscores": 0.995,
        "T4 Fscores": 0.984
    },
    {
        "Google Processor Name": "IL_Ver_B_Well_Completion",
        "OGRRE Document Type": "Well Completion Report Types B, C, D, E",
        "Page Order Sort": 48.0,
        "Name": "Was_Well_Cored_Yes",
        "Google Data type": "Checkbox",
        "Occurrence": "Optional once",
        "Grouping": "Was Well Cored",
        "Database Data Type": "bool",
        "Cleaning Function": "clean_bool",
        "Accepted Range": null,
        "Field Specific Notes": null,
        "Model Enabled": "Yes",
        "V1 Fscores": 0.644,
        "V2 Fscores": 0.637,
        "V3 Fscores": 0.637,
        "T1 Fscores": 0.563,
        "T2 Fscores": 0.619,
        "T3 Fscores": 0.592,
        "T4 Fscores": 0.604
    },
    {
        "Google Processor Name": "IL_Ver_B_Well_Completion",
        "OGRRE Document Type": "Well Completion Report Types B, C, D, E",
        "Page Order Sort": 49.0,
        "Name": "Was_Well_Cored_No",
        "Google Data type": "Checkbox",
        "Occurrence": "Optional once",
        "Grouping": "Was Well Cored",
        "Database Data Type": "bool",
        "Cleaning Function": "clean_bool",
        "Accepted Range": null,
        "Field Specific Notes": null,
        "Model Enabled": "Yes",
        "V1 Fscores": 0.755,
        "V2 Fscores": 0.771,
        "V3 Fscores": 0.734,
        "T1 Fscores": 0.648,
        "T2 Fscores": 0.739,
        "T3 Fscores": 0.649,
        "T4 Fscores": 0.71
    },
    {
        "Google Processor Name": "IL_Ver_B_Well_Completion",
        "OGRRE Document Type": "Well Completion Report Types B, C, D, E",
        "Page Order Sort": 50.0,
        "Name": "Interval_Cored",
        "Google Data type": "Plain text",
        "Occurrence": "Optional once",
        "Grouping": null,
        "Database Data Type": "str",
        "Cleaning Function": null,
        "Accepted Range": "[0-20000,]",
        "Field Specific Notes": "Max interval is 1000 ft, second number may be shortened such as 2068-77",
        "Model Enabled": "No",
        "V1 Fscores": null,
        "V2 Fscores": null,
        "V3 Fscores": null,
        "T1 Fscores": null,
        "T2 Fscores": null,
        "T3 Fscores": null,
        "T4 Fscores": null
    },
    {
        "Google Processor Name": "IL_Ver_B_Well_Completion",
        "OGRRE Document Type": "Well Completion Report Types B, C, D, E",
        "Page Order Sort": 51.0,
        "Name": "Drill_Stem_Test_Run_Yes",
        "Google Data type": "Checkbox",
        "Occurrence": "Optional once",
        "Grouping": "Drill Stem Test",
        "Database Data Type": "bool",
        "Cleaning Function": "clean_bool",
        "Accepted Range": null,
        "Field Specific Notes": null,
        "Model Enabled": "Yes",
        "V1 Fscores": 0.667,
        "V2 Fscores": 0.587,
        "V3 Fscores": 0.638,
        "T1 Fscores": 0.646,
        "T2 Fscores": 0.64,
        "T3 Fscores": 0.653,
        "T4 Fscores": 0.673
    },
    {
        "Google Processor Name": "IL_Ver_B_Well_Completion",
        "OGRRE Document Type": "Well Completion Report Types B, C, D, E",
        "Page Order Sort": 52.0,
        "Name": "Drill_Stem_Test_Run_No",
        "Google Data type": "Checkbox",
        "Occurrence": "Optional once",
        "Grouping": "Drill Stem Test",
        "Database Data Type": "bool",
        "Cleaning Function": "clean_bool",
        "Accepted Range": null,
        "Field Specific Notes": null,
        "Model Enabled": "Yes",
        "V1 Fscores": 0.66,
        "V2 Fscores": 0.674,
        "V3 Fscores": 0.667,
        "T1 Fscores": 0.752,
        "T2 Fscores": 0.75,
        "T3 Fscores": 0.709,
        "T4 Fscores": 0.741
    },
    {
        "Google Processor Name": "IL_Ver_B_Well_Completion",
        "OGRRE Document Type": "Well Completion Report Types B, C, D, E",
        "Page Order Sort": 53.0,
        "Name": "Zone_Tested",
        "Google Data type": "Plain text",
        "Occurrence": "Optional once",
        "Grouping": null,
        "Database Data Type": "str",
        "Cleaning Function": null,
        "Accepted Range": "A-z0-9{1,20}",
        "Field Specific Notes": null,
        "Model Enabled": "Yes",
        "V1 Fscores": 0.571,
        "V2 Fscores": 0.333,
        "V3 Fscores": 0.471,
        "T1 Fscores": 0.96,
        "T2 Fscores": 0.759,
        "T3 Fscores": 0.923,
        "T4 Fscores": 0.769
    },
    {
        "Google Processor Name": "IL_Ver_B_Well_Completion",
        "OGRRE Document Type": "Well Completion Report Types B, C, D, E",
        "Page Order Sort": 54.0,
        "Name": "Surface_Size",
        "Google Data type": "Plain text",
        "Occurrence": "Optional once",
        "Grouping": null,
        "Database Data Type": "float",
        "Cleaning Function": "convert_hole_size_to_decimal",
        "Accepted Range": null,
        "Field Specific Notes": null,
        "Model Enabled": "Yes",
        "V1 Fscores": 0.735,
        "V2 Fscores": 0.689,
        "V3 Fscores": 0.705,
        "T1 Fscores": 0.652,
        "T2 Fscores": 0.682,
        "T3 Fscores": 0.662,
        "T4 Fscores": 0.687
    },
    {
        "Google Processor Name": "IL_Ver_B_Well_Completion",
        "OGRRE Document Type": "Well Completion Report Types B, C, D, E",
        "Page Order Sort": 55.0,
        "Name": "Surface_Setting_Depth",
        "Google Data type": "Plain text",
        "Occurrence": "Optional once",
        "Grouping": null,
        "Database Data Type": "float",
        "Cleaning Function": "string_to_float",
        "Accepted Range": null,
        "Field Specific Notes": "{#, TD, Total Depth}, #==Float, TD and Total Depth ==Total_Depth",
        "Model Enabled": "Yes",
        "V1 Fscores": 0.926,
        "V2 Fscores": 0.919,
        "V3 Fscores": 0.924,
        "T1 Fscores": 0.948,
        "T2 Fscores": 0.94,
        "T3 Fscores": 0.9,
        "T4 Fscores": 0.92
    },
    {
        "Google Processor Name": "IL_Ver_B_Well_Completion",
        "OGRRE Document Type": "Well Completion Report Types B, C, D, E",
        "Page Order Sort": 56.0,
        "Name": "Surface_Sacks_Cement",
        "Google Data type": "Plain text",
        "Occurrence": "Optional once",
        "Grouping": null,
        "Database Data Type": "float",
        "Cleaning Function": "string_to_float",
        "Accepted Range": null,
        "Field Specific Notes": null,
        "Model Enabled": "Yes",
        "V1 Fscores": 0.823,
        "V2 Fscores": 0.832,
        "V3 Fscores": 0.829,
        "T1 Fscores": 0.929,
        "T2 Fscores": 0.899,
        "T3 Fscores": 0.865,
        "T4 Fscores": 0.892
    },
    {
        "Google Processor Name": "IL_Ver_B_Well_Completion",
        "OGRRE Document Type": "Well Completion Report Types B, C, D, E",
        "Page Order Sort": 57.0,
        "Name": "Surface_Hole_Size",
        "Google Data type": "Plain text",
        "Occurrence": "Optional once",
        "Grouping": null,
        "Database Data Type": "float",
        "Cleaning Function": "convert_hole_size_to_decimal",
        "Accepted Range": null,
        "Field Specific Notes": null,
        "Model Enabled": "Yes",
        "V1 Fscores": 0.677,
        "V2 Fscores": 0.687,
        "V3 Fscores": 0.672,
        "T1 Fscores": 0.688,
        "T2 Fscores": 0.712,
        "T3 Fscores": 0.682,
        "T4 Fscores": 0.656
    },
    {
        "Google Processor Name": "IL_Ver_B_Well_Completion",
        "OGRRE Document Type": "Well Completion Report Types B, C, D, E",
        "Page Order Sort": 58.0,
        "Name": "Surface_Top_Of_Cement",
        "Google Data type": "Plain text",
        "Occurrence": "Optional once",
        "Grouping": null,
        "Database Data Type": "float",
        "Cleaning Function": "string_to_float",
        "Accepted Range": null,
        "Field Specific Notes": "{#, TD, Total Depth, Surface}, #==Float, TD and Total Depth ==Total_Depth, Surface==0.0",
        "Model Enabled": "Yes",
        "V1 Fscores": 0.857,
        "V2 Fscores": 0.891,
        "V3 Fscores": 0.885,
        "T1 Fscores": 0.924,
        "T2 Fscores": 0.923,
        "T3 Fscores": 0.915,
        "T4 Fscores": 0.876
    },
    {
        "Google Processor Name": "IL_Ver_B_Well_Completion",
        "OGRRE Document Type": "Well Completion Report Types B, C, D, E",
        "Page Order Sort": 59.0,
        "Name": "Surface_Top_Determined_By",
        "Google Data type": "Plain text",
        "Occurrence": "Optional once",
        "Grouping": null,
        "Database Data Type": "str",
        "Cleaning Function": null,
        "Accepted Range": "A-z{1,20}",
        "Field Specific Notes": null,
        "Model Enabled": "Yes",
        "V1 Fscores": 0.654,
        "V2 Fscores": 0.678,
        "V3 Fscores": 0.721,
        "T1 Fscores": 0.922,
        "T2 Fscores": 0.841,
        "T3 Fscores": 0.836,
        "T4 Fscores": 0.748
    },
    {
        "Google Processor Name": "IL_Ver_B_Well_Completion",
        "OGRRE Document Type": "Well Completion Report Types B, C, D, E",
        "Page Order Sort": 60.0,
        "Name": "Intermedate_Mine_String_Or_Liner_Size",
        "Google Data type": "Plain text",
        "Occurrence": "Optional once",
        "Grouping": null,
        "Database Data Type": "float",
        "Cleaning Function": "convert_hole_size_to_decimal",
        "Accepted Range": null,
        "Field Specific Notes": null,
        "Model Enabled": "Yes",
        "V1 Fscores": 0.783,
        "V2 Fscores": 0.818,
        "V3 Fscores": 0.87,
        "T1 Fscores": 0.88,
        "T2 Fscores": 0.88,
        "T3 Fscores": 0.8,
        "T4 Fscores": 0.72
    },
    {
        "Google Processor Name": "IL_Ver_B_Well_Completion",
        "OGRRE Document Type": "Well Completion Report Types B, C, D, E",
        "Page Order Sort": 61.0,
        "Name": "Intermedate_Mine_String_Or_Liner_Setting_Depth",
        "Google Data type": "Plain text",
        "Occurrence": "Optional once",
        "Grouping": null,
        "Database Data Type": "float",
        "Cleaning Function": "string_to_float",
        "Accepted Range": null,
        "Field Specific Notes": "{#, TD, Total Depth}, #==Float, TD and Total Depth ==Total_Depth",
        "Model Enabled": "Yes",
        "V1 Fscores": 0.588,
        "V2 Fscores": 0.588,
        "V3 Fscores": 0.588,
        "T1 Fscores": 1.0,
        "T2 Fscores": 0.857,
        "T3 Fscores": 0.917,
        "T4 Fscores": 0.846
    },
    {
        "Google Processor Name": "IL_Ver_B_Well_Completion",
        "OGRRE Document Type": "Well Completion Report Types B, C, D, E",
        "Page Order Sort": 62.0,
        "Name": "Intermedate_Mine_String_Or_Liner_Sacks_Cement",
        "Google Data type": "Plain text",
        "Occurrence": "Optional once",
        "Grouping": null,
        "Database Data Type": "float",
        "Cleaning Function": "string_to_float",
        "Accepted Range": null,
        "Field Specific Notes": null,
        "Model Enabled": "Yes",
        "V1 Fscores": 0.5,
        "V2 Fscores": 0.5,
        "V3 Fscores": 0.5,
        "T1 Fscores": 0.769,
        "T2 Fscores": 0.714,
        "T3 Fscores": 0.8,
        "T4 Fscores": 0.8
    },
    {
        "Google Processor Name": "IL_Ver_B_Well_Completion",
        "OGRRE Document Type": "Well Completion Report Types B, C, D, E",
        "Page Order Sort": 63.0,
        "Name": "Intermedate_Mine_String_Or_Liner_Hole_Size",
        "Google Data type": "Plain text",
        "Occurrence": "Optional once",
        "Grouping": null,
        "Database Data Type": "float",
        "Cleaning Function": "convert_hole_size_to_decimal",
        "Accepted Range": null,
        "Field Specific Notes": null,
        "Model Enabled": "Yes",
        "V1 Fscores": 0.667,
        "V2 Fscores": 0.588,
        "V3 Fscores": 0.737,
        "T1 Fscores": 0.917,
        "T2 Fscores": 0.87,
        "T3 Fscores": 0.917,
        "T4 Fscores": 0.88
    },
    {
        "Google Processor Name": "IL_Ver_B_Well_Completion",
        "OGRRE Document Type": "Well Completion Report Types B, C, D, E",
        "Page Order Sort": 64.0,
        "Name": "Intermedate_Mine_String_Or_Liner_Top_Of_Cement",
        "Google Data type": "Plain text",
        "Occurrence": "Optional once",
        "Grouping": null,
        "Database Data Type": "float",
        "Cleaning Function": "string_to_float",
        "Accepted Range": null,
        "Field Specific Notes": "{#, TD, Total Depth, Surface}, #==Float, TD and Total Depth ==Total_Depth, Surface==0.0",
        "Model Enabled": "Yes",
        "V1 Fscores": 0.737,
        "V2 Fscores": 0.824,
        "V3 Fscores": 0.824,
        "T1 Fscores": 0.947,
        "T2 Fscores": 0.783,
        "T3 Fscores": 0.842,
        "T4 Fscores": 0.818
    },
    {
        "Google Processor Name": "IL_Ver_B_Well_Completion",
        "OGRRE Document Type": "Well Completion Report Types B, C, D, E",
        "Page Order Sort": 65.0,
        "Name": "Intermedate_Mine_String_Or_Liner_Top_Determined_By",
        "Google Data type": "Plain text",
        "Occurrence": "Optional once",
        "Grouping": null,
        "Database Data Type": "str",
        "Cleaning Function": null,
        "Accepted Range": "A-z{1,20}",
        "Field Specific Notes": null,
        "Model Enabled": "Yes",
        "V1 Fscores": 0.286,
        "V2 Fscores": 0.5,
        "V3 Fscores": 0.471,
        "T1 Fscores": 0.857,
        "T2 Fscores": 0.8,
        "T3 Fscores": 0.87,
        "T4 Fscores": 0.783
    },
    {
        "Google Processor Name": "IL_Ver_B_Well_Completion",
        "OGRRE Document Type": "Well Completion Report Types B, C, D, E",
        "Page Order Sort": 66.0,
        "Name": "Production_Size",
        "Google Data type": "Plain text",
        "Occurrence": "Optional once",
        "Grouping": null,
        "Database Data Type": "float",
        "Cleaning Function": "convert_hole_size_to_decimal",
        "Accepted Range": null,
        "Field Specific Notes": null,
        "Model Enabled": "Yes",
        "V1 Fscores": 0.629,
        "V2 Fscores": 0.625,
        "V3 Fscores": 0.63,
        "T1 Fscores": 0.612,
        "T2 Fscores": 0.597,
        "T3 Fscores": 0.609,
        "T4 Fscores": 0.607
    },
    {
        "Google Processor Name": "IL_Ver_B_Well_Completion",
        "OGRRE Document Type": "Well Completion Report Types B, C, D, E",
        "Page Order Sort": 67.0,
        "Name": "Production_Setting_Depth",
        "Google Data type": "Plain text",
        "Occurrence": "Optional once",
        "Grouping": null,
        "Database Data Type": "float",
        "Cleaning Function": "string_to_float",
        "Accepted Range": null,
        "Field Specific Notes": "{#, TD, Total Depth}, #==Float, TD and Total Depth ==Total_Depth",
        "Model Enabled": "Yes",
        "V1 Fscores": 0.924,
        "V2 Fscores": 0.926,
        "V3 Fscores": 0.787,
        "T1 Fscores": 0.992,
        "T2 Fscores": 0.984,
        "T3 Fscores": 0.976,
        "T4 Fscores": 0.934
    },
    {
        "Google Processor Name": "IL_Ver_B_Well_Completion",
        "OGRRE Document Type": "Well Completion Report Types B, C, D, E",
        "Page Order Sort": 68.0,
        "Name": "Production_Sacks_Cement",
        "Google Data type": "Plain text",
        "Occurrence": "Optional once",
        "Grouping": null,
        "Database Data Type": "float",
        "Cleaning Function": "string_to_float",
        "Accepted Range": null,
        "Field Specific Notes": null,
        "Model Enabled": "Yes",
        "V1 Fscores": 0.793,
        "V2 Fscores": 0.811,
        "V3 Fscores": 0.818,
        "T1 Fscores": 0.931,
        "T2 Fscores": 0.897,
        "T3 Fscores": 0.879,
        "T4 Fscores": 0.85
    },
    {
        "Google Processor Name": "IL_Ver_B_Well_Completion",
        "OGRRE Document Type": "Well Completion Report Types B, C, D, E",
        "Page Order Sort": 69.0,
        "Name": "Production_Hole_Size",
        "Google Data type": "Plain text",
        "Occurrence": "Optional once",
        "Grouping": null,
        "Database Data Type": "float",
        "Cleaning Function": "convert_hole_size_to_decimal",
        "Accepted Range": null,
        "Field Specific Notes": null,
        "Model Enabled": "Yes",
        "V1 Fscores": 0.629,
        "V2 Fscores": 0.571,
        "V3 Fscores": 0.667,
        "T1 Fscores": 0.673,
        "T2 Fscores": 0.647,
        "T3 Fscores": 0.632,
        "T4 Fscores": 0.6
    },
    {
        "Google Processor Name": "IL_Ver_B_Well_Completion",
        "OGRRE Document Type": "Well Completion Report Types B, C, D, E",
        "Page Order Sort": 70.0,
        "Name": "Production_Top_Of_Cement",
        "Google Data type": "Plain text",
        "Occurrence": "Optional once",
        "Grouping": null,
        "Database Data Type": "float",
        "Cleaning Function": "string_to_float",
        "Accepted Range": null,
        "Field Specific Notes": "{#, TD, Total Depth, Surface}, #==Float, TD and Total Depth ==Total_Depth, Surface==0.0",
        "Model Enabled": "Yes",
        "V1 Fscores": 0.667,
        "V2 Fscores": 0.646,
        "V3 Fscores": 0.693,
        "T1 Fscores": 0.927,
        "T2 Fscores": 0.926,
        "T3 Fscores": 0.865,
        "T4 Fscores": 0.86
    },
    {
        "Google Processor Name": "IL_Ver_B_Well_Completion",
        "OGRRE Document Type": "Well Completion Report Types B, C, D, E",
        "Page Order Sort": 71.0,
        "Name": "Production_Top_Determined_By",
        "Google Data type": "Plain text",
        "Occurrence": "Optional once",
        "Grouping": null,
        "Database Data Type": "str",
        "Cleaning Function": null,
        "Accepted Range": "A-z{1,20}",
        "Field Specific Notes": null,
        "Model Enabled": "Yes",
        "V1 Fscores": 0.513,
        "V2 Fscores": 0.587,
        "V3 Fscores": 0.593,
        "T1 Fscores": 0.913,
        "T2 Fscores": 0.833,
        "T3 Fscores": 0.725,
        "T4 Fscores": 0.72
    },
    {
        "Google Processor Name": "IL_Ver_B_Well_Completion",
        "OGRRE Document Type": "Well Completion Report Types B, C, D, E",
        "Page Order Sort": 72.0,
        "Name": "Other_Size",
        "Google Data type": "Plain text",
        "Occurrence": "Optional once",
        "Grouping": null,
        "Database Data Type": "float",
        "Cleaning Function": "convert_hole_size_to_decimal",
        "Accepted Range": null,
        "Field Specific Notes": null,
        "Model Enabled": "No",
        "V1 Fscores": null,
        "V2 Fscores": null,
        "V3 Fscores": null,
        "T1 Fscores": null,
        "T2 Fscores": null,
        "T3 Fscores": null,
        "T4 Fscores": null
    },
    {
        "Google Processor Name": "IL_Ver_B_Well_Completion",
        "OGRRE Document Type": "Well Completion Report Types B, C, D, E",
        "Page Order Sort": 73.0,
        "Name": "Other_Setting_Depth",
        "Google Data type": "Plain text",
        "Occurrence": "Optional once",
        "Grouping": null,
        "Database Data Type": "float",
        "Cleaning Function": "string_to_float",
        "Accepted Range": null,
        "Field Specific Notes": "{#, TD, Total Depth}, #==Float, TD and Total Depth ==Total_Depth",
        "Model Enabled": "No",
        "V1 Fscores": null,
        "V2 Fscores": null,
        "V3 Fscores": null,
        "T1 Fscores": null,
        "T2 Fscores": null,
        "T3 Fscores": null,
        "T4 Fscores": null
    },
    {
        "Google Processor Name": "IL_Ver_B_Well_Completion",
        "OGRRE Document Type": "Well Completion Report Types B, C, D, E",
        "Page Order Sort": 74.0,
        "Name": "Other_Sacks_Cement",
        "Google Data type": "Plain text",
        "Occurrence": "Optional once",
        "Grouping": null,
        "Database Data Type": "float",
        "Cleaning Function": "string_to_float",
        "Accepted Range": null,
        "Field Specific Notes": null,
        "Model Enabled": "No",
        "V1 Fscores": null,
        "V2 Fscores": null,
        "V3 Fscores": null,
        "T1 Fscores": null,
        "T2 Fscores": null,
        "T3 Fscores": null,
        "T4 Fscores": null
    },
    {
        "Google Processor Name": "IL_Ver_B_Well_Completion",
        "OGRRE Document Type": "Well Completion Report Types B, C, D, E",
        "Page Order Sort": 75.0,
        "Name": "Other_Hole_Size",
        "Google Data type": "Plain text",
        "Occurrence": "Optional once",
        "Grouping": null,
        "Database Data Type": "float",
        "Cleaning Function": "convert_hole_size_to_decimal",
        "Accepted Range": null,
        "Field Specific Notes": null,
        "Model Enabled": "No",
        "V1 Fscores": null,
        "V2 Fscores": null,
        "V3 Fscores": null,
        "T1 Fscores": null,
        "T2 Fscores": null,
        "T3 Fscores": null,
        "T4 Fscores": null
    },
    {
        "Google Processor Name": "IL_Ver_B_Well_Completion",
        "OGRRE Document Type": "Well Completion Report Types B, C, D, E",
        "Page Order Sort": 76.0,
        "Name": "Other_Top_Of_Cement",
        "Google Data type": "Plain text",
        "Occurrence": "Optional once",
        "Grouping": null,
        "Database Data Type": "float",
        "Cleaning Function": "string_to_float",
        "Accepted Range": null,
        "Field Specific Notes": "{#, TD, Total Depth, Surface}, #==Float, TD and Total Depth ==Total_Depth, Surface==0.0",
        "Model Enabled": "No",
        "V1 Fscores": null,
        "V2 Fscores": null,
        "V3 Fscores": null,
        "T1 Fscores": null,
        "T2 Fscores": null,
        "T3 Fscores": null,
        "T4 Fscores": null
    },
    {
        "Google Processor Name": "IL_Ver_B_Well_Completion",
        "OGRRE Document Type": "Well Completion Report Types B, C, D, E",
        "Page Order Sort": 77.0,
        "Name": "Other_Top_Determined_By",
        "Google Data type": "Plain text",
        "Occurrence": "Optional once",
        "Grouping": null,
        "Database Data Type": "str",
        "Cleaning Function": null,
        "Accepted Range": "A-z{1,20}",
        "Field Specific Notes": null,
        "Model Enabled": "No",
        "V1 Fscores": null,
        "V2 Fscores": null,
        "V3 Fscores": null,
        "T1 Fscores": null,
        "T2 Fscores": null,
        "T3 Fscores": null,
        "T4 Fscores": null
    },
    {
        "Google Processor Name": "IL_Ver_B_Well_Completion",
        "OGRRE Document Type": "Well Completion Report Types B, C, D, E",
        "Page Order Sort": 78.0,
        "Name": "Tubing_Type",
        "Google Data type": "Plain text",
        "Occurrence": "Optional once",
        "Grouping": null,
        "Database Data Type": "str",
        "Cleaning Function": null,
        "Accepted Range": "A-z0-9{1,20}",
        "Field Specific Notes": null,
        "Model Enabled": "Yes",
        "V1 Fscores": 0.75,
        "V2 Fscores": 0.651,
        "V3 Fscores": 0.731,
        "T1 Fscores": 0.832,
        "T2 Fscores": 0.849,
        "T3 Fscores": 0.82,
        "T4 Fscores": 0.822
    },
    {
        "Google Processor Name": "IL_Ver_B_Well_Completion",
        "OGRRE Document Type": "Well Completion Report Types B, C, D, E",
        "Page Order Sort": 79.0,
        "Name": "Tubing_Size",
        "Google Data type": "Plain text",
        "Occurrence": "Optional once",
        "Grouping": null,
        "Database Data Type": "float",
        "Cleaning Function": "convert_hole_size_to_decimal",
        "Accepted Range": null,
        "Field Specific Notes": null,
        "Model Enabled": "Yes",
        "V1 Fscores": 0.681,
        "V2 Fscores": 0.722,
        "V3 Fscores": 0.74,
        "T1 Fscores": 653.0,
        "T2 Fscores": 0.717,
        "T3 Fscores": 0.69,
        "T4 Fscores": 0.685
    },
    {
        "Google Processor Name": "IL_Ver_B_Well_Completion",
        "OGRRE Document Type": "Well Completion Report Types B, C, D, E",
        "Page Order Sort": 80.0,
        "Name": "Packer",
        "Google Data type": "Parent",
        "Occurrence": "Optional multiple",
        "Grouping": null,
        "Database Data Type": "Table",
        "Cleaning Function": null,
        "Accepted Range": null,
        "Field Specific Notes": null,
        "Model Enabled": "Yes",
        "V1 Fscores": null,
        "V2 Fscores": null,
        "V3 Fscores": 0.592,
        "T1 Fscores": null,
        "T2 Fscores": null,
        "T3 Fscores": 0.921,
        "T4 Fscores": 0.905
    },
    {
        "Google Processor Name": "IL_Ver_B_Well_Completion",
        "OGRRE Document Type": "Well Completion Report Types B, C, D, E",
        "Page Order Sort": 81.0,
        "Name": "Packer::Brand_And_Type",
        "Google Data type": "Plain text",
        "Occurrence": "Optional once",
        "Grouping": null,
        "Database Data Type": "str",
        "Cleaning Function": null,
        "Accepted Range": "A-z0-9{1,20}",
        "Field Specific Notes": "{#, TD, Total Depth}, #==Float, TD and Total Depth ==Total_Depth",
        "Model Enabled": "Yes",
        "V1 Fscores": 0.75,
        "V2 Fscores": 0.783,
        "V3 Fscores": null,
        "T1 Fscores": 0.902,
        "T2 Fscores": 0.943,
        "T3 Fscores": null,
        "T4 Fscores": null
    },
    {
        "Google Processor Name": "IL_Ver_B_Well_Completion",
        "OGRRE Document Type": "Well Completion Report Types B, C, D, E",
        "Page Order Sort": 82.0,
        "Name": "Packer::Setting_Depth",
        "Google Data type": "Plain text",
        "Occurrence": "Optional once",
        "Grouping": null,
        "Database Data Type": "float",
        "Cleaning Function": "string_to_float",
        "Accepted Range": null,
        "Field Specific Notes": "{#, TD, Total Depth}, #==Float, TD and Total Depth ==Total_Depth",
        "Model Enabled": "Yes",
        "V1 Fscores": 0.97,
        "V2 Fscores": 0.944,
        "V3 Fscores": null,
        "T1 Fscores": 0.903,
        "T2 Fscores": 0.971,
        "T3 Fscores": null,
        "T4 Fscores": null
    },
    {
        "Google Processor Name": "IL_Ver_B_Well_Completion",
        "OGRRE Document Type": "Well Completion Report Types B, C, D, E",
        "Page Order Sort": 83.0,
        "Name": "Completion_For_Production",
        "Google Data type": "Parent",
        "Occurrence": "Optional multiple",
        "Grouping": null,
        "Database Data Type": "Table",
        "Cleaning Function": null,
        "Accepted Range": null,
        "Field Specific Notes": null,
        "Model Enabled": "Yes",
        "V1 Fscores": 0.693,
        "V2 Fscores": 0.527,
        "V3 Fscores": 0.642,
        "T1 Fscores": 0.746,
        "T2 Fscores": 0.891,
        "T3 Fscores": 0.788,
        "T4 Fscores": 0.848
    },
    {
        "Google Processor Name": "IL_Ver_B_Well_Completion",
        "OGRRE Document Type": "Well Completion Report Types B, C, D, E",
        "Page Order Sort": 84.0,
        "Name": "Completion_For_Production::Formation_Name",
        "Google Data type": "Plain text",
        "Occurrence": "Optional multiple",
        "Grouping": null,
        "Database Data Type": "str",
        "Cleaning Function": null,
        "Accepted Range": "A-z{1,30}",
        "Field Specific Notes": null,
        "Model Enabled": "Yes",
        "V1 Fscores": 0.8,
        "V2 Fscores": 0.635,
        "V3 Fscores": 0.696,
        "T1 Fscores": 0.776,
        "T2 Fscores": 0.929,
        "T3 Fscores": 0.785,
        "T4 Fscores": 0.844
    },
    {
        "Google Processor Name": "IL_Ver_B_Well_Completion",
        "OGRRE Document Type": "Well Completion Report Types B, C, D, E",
        "Page Order Sort": 85.0,
        "Name": "Completion_For_Production::Lithology",
        "Google Data type": "Plain text",
        "Occurrence": "Optional multiple",
        "Grouping": null,
        "Database Data Type": "str",
        "Cleaning Function": null,
        "Accepted Range": "A-z{1,30}",
        "Field Specific Notes": null,
        "Model Enabled": "Yes",
        "V1 Fscores": 0.648,
        "V2 Fscores": 0.608,
        "V3 Fscores": 0.636,
        "T1 Fscores": 0.803,
        "T2 Fscores": 0.926,
        "T3 Fscores": 0.828,
        "T4 Fscores": 0.841
    },
    {
        "Google Processor Name": "IL_Ver_B_Well_Completion",
        "OGRRE Document Type": "Well Completion Report Types B, C, D, E",
        "Page Order Sort": 86.0,
        "Name": "Completion_For_Production::Perforation_Interval",
        "Google Data type": "Plain text",
        "Occurrence": "Optional multiple",
        "Grouping": null,
        "Database Data Type": "str",
        "Cleaning Function": null,
        "Accepted Range": "[0-20000,]",
        "Field Specific Notes": "Max interval is 1000 ft",
        "Model Enabled": "Yes",
        "V1 Fscores": 0.771,
        "V2 Fscores": 0.549,
        "V3 Fscores": 0.653,
        "T1 Fscores": 0.745,
        "T2 Fscores": 0.877,
        "T3 Fscores": 0.789,
        "T4 Fscores": 0.837
    },
    {
        "Google Processor Name": "IL_Ver_B_Well_Completion",
        "OGRRE Document Type": "Well Completion Report Types B, C, D, E",
        "Page Order Sort": 87.0,
        "Name": "Completion_For_Production::Shots",
        "Google Data type": "Plain text",
        "Occurrence": "Optional multiple",
        "Grouping": null,
        "Database Data Type": "float",
        "Cleaning Function": "string_to_float",
        "Accepted Range": null,
        "Field Specific Notes": null,
        "Model Enabled": "Yes",
        "V1 Fscores": 0.758,
        "V2 Fscores": 0.735,
        "V3 Fscores": 0.686,
        "T1 Fscores": 0.712,
        "T2 Fscores": 0.925,
        "T3 Fscores": 0.687,
        "T4 Fscores": 0.896
    },
    {
        "Google Processor Name": "IL_Ver_B_Well_Completion",
        "OGRRE Document Type": "Well Completion Report Types B, C, D, E",
        "Page Order Sort": 88.0,
        "Name": "Completion_For_Production::Open_Hole_Interval",
        "Google Data type": "Plain text",
        "Occurrence": "Optional multiple",
        "Grouping": null,
        "Database Data Type": "str",
        "Cleaning Function": null,
        "Accepted Range": "[0-20000,]",
        "Field Specific Notes": "Max interval is 1000 ft",
        "Model Enabled": "No",
        "V1 Fscores": null,
        "V2 Fscores": null,
        "V3 Fscores": null,
        "T1 Fscores": null,
        "T2 Fscores": null,
        "T3 Fscores": null,
        "T4 Fscores": null
    },
    {
        "Google Processor Name": "IL_Ver_B_Well_Completion",
        "OGRRE Document Type": "Well Completion Report Types B, C, D, E",
        "Page Order Sort": 89.0,
        "Name": "Completion_For_Production::Acidized_Fractures_Other",
        "Google Data type": "Plain text",
        "Occurrence": "Optional multiple",
        "Grouping": null,
        "Database Data Type": "str",
        "Cleaning Function": null,
        "Accepted Range": "A-z0-9{1,60}",
        "Field Specific Notes": null,
        "Model Enabled": "Yes",
        "V1 Fscores": 0.6,
        "V2 Fscores": 0.301,
        "V3 Fscores": 0.558,
        "T1 Fscores": 0.688,
        "T2 Fscores": 0.839,
        "T3 Fscores": 0.786,
        "T4 Fscores": 0.871
    },
    {
        "Google Processor Name": "IL_Ver_B_Well_Completion",
        "OGRRE Document Type": "Well Completion Report Types B, C, D, E",
        "Page Order Sort": 90.0,
        "Name": "Producing_Formations",
        "Google Data type": "Plain text",
        "Occurrence": "Optional once",
        "Grouping": null,
        "Database Data Type": "str",
        "Cleaning Function": null,
        "Accepted Range": "A-z{1,30}",
        "Field Specific Notes": null,
        "Model Enabled": "Yes",
        "V1 Fscores": 0.818,
        "V2 Fscores": 0.909,
        "V3 Fscores": 0.889,
        "T1 Fscores": 0.753,
        "T2 Fscores": 0.882,
        "T3 Fscores": 0.96,
        "T4 Fscores": 0.97
    },
    {
        "Google Processor Name": "IL_Ver_B_Well_Completion",
        "OGRRE Document Type": "Well Completion Report Types B, C, D, E",
        "Page Order Sort": 91.0,
        "Name": "Date_Of_First_Production",
        "Google Data type": "Plain text",
        "Occurrence": "Optional once",
        "Grouping": null,
        "Database Data Type": "date",
        "Cleaning Function": "clean_date",
        "Accepted Range": null,
        "Field Specific Notes": null,
        "Model Enabled": "Yes",
        "V1 Fscores": 0.939,
        "V2 Fscores": 0.928,
        "V3 Fscores": 0.912,
        "T1 Fscores": 0.679,
        "T2 Fscores": 0.912,
        "T3 Fscores": 0.928,
        "T4 Fscores": 0.912
    },
    {
        "Google Processor Name": "IL_Ver_B_Well_Completion",
        "OGRRE Document Type": "Well Completion Report Types B, C, D, E",
        "Page Order Sort": 92.0,
        "Name": "Date_Of_Test",
        "Google Data type": "Plain text",
        "Occurrence": "Optional once",
        "Grouping": null,
        "Database Data Type": "date",
        "Cleaning Function": "clean_date",
        "Accepted Range": null,
        "Field Specific Notes": null,
        "Model Enabled": "Yes",
        "V1 Fscores": 0.962,
        "V2 Fscores": 0.963,
        "V3 Fscores": 0.945,
        "T1 Fscores": 0.667,
        "T2 Fscores": 0.963,
        "T3 Fscores": 0.897,
        "T4 Fscores": 0.929
    },
    {
        "Google Processor Name": "IL_Ver_B_Well_Completion",
        "OGRRE Document Type": "Well Completion Report Types B, C, D, E",
        "Page Order Sort": 93.0,
        "Name": "Length_Of_Test",
        "Google Data type": "Plain text",
        "Occurrence": "Optional once",
        "Grouping": null,
        "Database Data Type": "float",
        "Cleaning Function": "string_to_float",
        "Accepted Range": null,
        "Field Specific Notes": null,
        "Model Enabled": "Yes",
        "V1 Fscores": 0.912,
        "V2 Fscores": 0.93,
        "V3 Fscores": 0.928,
        "T1 Fscores": 0.774,
        "T2 Fscores": 0.93,
        "T3 Fscores": 0.986,
        "T4 Fscores": 0.914
    },
    {
        "Google Processor Name": "IL_Ver_B_Well_Completion",
        "OGRRE Document Type": "Well Completion Report Types B, C, D, E",
        "Page Order Sort": 94.0,
        "Name": "Initial_Production_Rate_Oil",
        "Google Data type": "Plain text",
        "Occurrence": "Optional once",
        "Grouping": null,
        "Database Data Type": "float",
        "Cleaning Function": "string_to_float",
        "Accepted Range": null,
        "Field Specific Notes": null,
        "Model Enabled": "Yes",
        "V1 Fscores": 0.929,
        "V2 Fscores": 0.941,
        "V3 Fscores": 0.909,
        "T1 Fscores": 0.74,
        "T2 Fscores": 0.941,
        "T3 Fscores": 0.93,
        "T4 Fscores": 0.92
    },
    {
        "Google Processor Name": "IL_Ver_B_Well_Completion",
        "OGRRE Document Type": "Well Completion Report Types B, C, D, E",
        "Page Order Sort": 95.0,
        "Name": "Initial_Production_Rate_Water",
        "Google Data type": "Plain text",
        "Occurrence": "Optional once",
        "Grouping": null,
        "Database Data Type": "float",
        "Cleaning Function": "string_to_float",
        "Accepted Range": null,
        "Field Specific Notes": null,
        "Model Enabled": "Yes",
        "V1 Fscores": 0.919,
        "V2 Fscores": 0.933,
        "V3 Fscores": 0.933,
        "T1 Fscores": 0.758,
        "T2 Fscores": 0.921,
        "T3 Fscores": 0.921,
        "T4 Fscores": 0.907
    },
    {
        "Google Processor Name": "IL_Ver_B_Well_Completion",
        "OGRRE Document Type": "Well Completion Report Types B, C, D, E",
        "Page Order Sort": 96.0,
        "Name": "Initial_Production_Rate_Gas",
        "Google Data type": "Plain text",
        "Occurrence": "Optional once",
        "Grouping": null,
        "Database Data Type": "float",
        "Cleaning Function": "string_to_float",
        "Accepted Range": null,
        "Field Specific Notes": null,
        "Model Enabled": "Yes",
        "V1 Fscores": 0.778,
        "V2 Fscores": 0.8,
        "V3 Fscores": 0.778,
        "T1 Fscores": 0.706,
        "T2 Fscores": 0.8,
        "T3 Fscores": 0.818,
        "T4 Fscores": 0.8
    },
    {
        "Google Processor Name": "IL_Ver_B_Well_Completion",
        "OGRRE Document Type": "Well Completion Report Types B, C, D, E",
        "Page Order Sort": 97.0,
        "Name": "Injection_Formation",
        "Google Data type": "Plain text",
        "Occurrence": "Optional once",
        "Grouping": null,
        "Database Data Type": "float",
        "Cleaning Function": "string_to_float",
        "Accepted Range": null,
        "Field Specific Notes": null,
        "Model Enabled": "Yes",
        "V1 Fscores": 0.789,
        "V2 Fscores": 0.788,
        "V3 Fscores": 0.875,
        "T1 Fscores": 0.593,
        "T2 Fscores": 0.857,
        "T3 Fscores": 0.944,
        "T4 Fscores": 0.824
    },
    {
        "Google Processor Name": "IL_Ver_B_Well_Completion",
        "OGRRE Document Type": "Well Completion Report Types B, C, D, E",
        "Page Order Sort": 98.0,
        "Name": "Type_Of_Injection_Fluid_Freshwater",
        "Google Data type": "Checkbox",
        "Occurrence": "Optional once",
        "Grouping": "Type of Injection Fluid",
        "Database Data Type": "bool",
        "Cleaning Function": "clean_bool",
        "Accepted Range": null,
        "Field Specific Notes": null,
        "Model Enabled": "Yes",
        "V1 Fscores": 0.943,
        "V2 Fscores": 0.944,
        "V3 Fscores": 0.944,
        "T1 Fscores": 0.786,
        "T2 Fscores": 0.944,
        "T3 Fscores": 0.944,
        "T4 Fscores": 0.944
    },
    {
        "Google Processor Name": "IL_Ver_B_Well_Completion",
        "OGRRE Document Type": "Well Completion Report Types B, C, D, E",
        "Page Order Sort": 99.0,
        "Name": "Type_Of_Injection_Fluid_Saltwater",
        "Google Data type": "Checkbox",
        "Occurrence": "Optional once",
        "Grouping": "Type of Injection Fluid",
        "Database Data Type": "bool",
        "Cleaning Function": "clean_bool",
        "Accepted Range": null,
        "Field Specific Notes": null,
        "Model Enabled": "Yes",
        "V1 Fscores": 0.956,
        "V2 Fscores": 0.957,
        "V3 Fscores": 0.943,
        "T1 Fscores": 0.8,
        "T2 Fscores": 0.957,
        "T3 Fscores": 0.95,
        "T4 Fscores": 0.95
    },
    {
        "Google Processor Name": "IL_Ver_B_Well_Completion",
        "OGRRE Document Type": "Well Completion Report Types B, C, D, E",
        "Page Order Sort": 100.0,
        "Name": "Type_Of_Injection_Fluid_Other",
        "Google Data type": "Checkbox",
        "Occurrence": "Optional once",
        "Grouping": "Type of Injection Fluid",
        "Database Data Type": "bool",
        "Cleaning Function": "clean_bool",
        "Accepted Range": null,
        "Field Specific Notes": null,
        "Model Enabled": "Yes",
        "V1 Fscores": 0.943,
        "V2 Fscores": 0.963,
        "V3 Fscores": 0.957,
        "T1 Fscores": 0.8,
        "T2 Fscores": 0.957,
        "T3 Fscores": 0.957,
        "T4 Fscores": 0.938
    },
    {
        "Google Processor Name": "IL_Ver_B_Well_Completion",
        "OGRRE Document Type": "Well Completion Report Types B, C, D, E",
        "Page Order Sort": 101.0,
        "Name": "Type_Of_Injection_Fluid_Other_Text",
        "Google Data type": "Plain text",
        "Occurrence": "Optional once",
        "Grouping": "Type of Injection Fluid",
        "Database Data Type": "str",
        "Cleaning Function": null,
        "Accepted Range": "A-z0-9{1,30}",
        "Field Specific Notes": null,
        "Model Enabled": "No",
        "V1 Fscores": null,
        "V2 Fscores": null,
        "V3 Fscores": null,
        "T1 Fscores": null,
        "T2 Fscores": null,
        "T3 Fscores": null,
        "T4 Fscores": null
    },
    {
        "Google Processor Name": "IL_Ver_B_Well_Completion",
        "OGRRE Document Type": "Well Completion Report Types B, C, D, E",
        "Page Order Sort": 102.0,
        "Name": "Source_Of_Injected_Fluid",
        "Google Data type": "Plain text",
        "Occurrence": "Optional once",
        "Grouping": null,
        "Database Data Type": "str",
        "Cleaning Function": null,
        "Accepted Range": "A-z0-9{1,60}",
        "Field Specific Notes": null,
        "Model Enabled": "Yes",
        "V1 Fscores": 0.556,
        "V2 Fscores": 0.588,
        "V3 Fscores": 0.588,
        "T1 Fscores": 0.588,
        "T2 Fscores": 1.0,
        "T3 Fscores": 1.0,
        "T4 Fscores": 0.917
    },
    {
        "Google Processor Name": "IL_Ver_B_Well_Completion",
        "OGRRE Document Type": "Well Completion Report Types B, C, D, E",
        "Page Order Sort": 103.0,
        "Name": "Date_Of_First_Injection",
        "Google Data type": "Datetime",
        "Occurrence": "Optional once",
        "Grouping": null,
        "Database Data Type": "date",
        "Cleaning Function": "clean_date",
        "Accepted Range": null,
        "Field Specific Notes": null,
        "Model Enabled": "Yes",
        "V1 Fscores": 1.0,
        "V2 Fscores": 1.0,
        "V3 Fscores": 1.0,
        "T1 Fscores": 0.588,
        "T2 Fscores": 1.0,
        "T3 Fscores": 1.0,
        "T4 Fscores": 1.0
    },
    {
        "Google Processor Name": "IL_Ver_B_Well_Completion",
        "OGRRE Document Type": "Well Completion Report Types B, C, D, E",
        "Page Order Sort": 104.0,
        "Name": "Rate_Per_Day_Water",
        "Google Data type": "Plain text",
        "Occurrence": "Optional once",
        "Grouping": null,
        "Database Data Type": "float",
        "Cleaning Function": "string_to_float",
        "Accepted Range": null,
        "Field Specific Notes": null,
        "Model Enabled": "Yes",
        "V1 Fscores": 0.947,
        "V2 Fscores": 0.947,
        "V3 Fscores": 0.947,
        "T1 Fscores": 0.533,
        "T2 Fscores": 0.9,
        "T3 Fscores": 0.952,
        "T4 Fscores": 0.909
    },
    {
        "Google Processor Name": "IL_Ver_B_Well_Completion",
        "OGRRE Document Type": "Well Completion Report Types B, C, D, E",
        "Page Order Sort": 105.0,
        "Name": "Water_PSI",
        "Google Data type": "Plain text",
        "Occurrence": "Optional once",
        "Grouping": null,
        "Database Data Type": "float",
        "Cleaning Function": "string_to_float",
        "Accepted Range": null,
        "Field Specific Notes": null,
        "Model Enabled": "Yes",
        "V1 Fscores": 0.9,
        "V2 Fscores": 0.909,
        "V3 Fscores": 0.952,
        "T1 Fscores": 0.533,
        "T2 Fscores": 0.9,
        "T3 Fscores": 0.8,
        "T4 Fscores": 0.952
    },
    {
        "Google Processor Name": "IL_Ver_B_Well_Completion",
        "OGRRE Document Type": "Well Completion Report Types B, C, D, E",
        "Page Order Sort": 106.0,
        "Name": "Rate_Per_Day_Gas",
        "Google Data type": "Plain text",
        "Occurrence": "Optional once",
        "Grouping": null,
        "Database Data Type": "float",
        "Cleaning Function": "string_to_float",
        "Accepted Range": null,
        "Field Specific Notes": null,
        "Model Enabled": "No",
        "V1 Fscores": null,
        "V2 Fscores": null,
        "V3 Fscores": null,
        "T1 Fscores": null,
        "T2 Fscores": null,
        "T3 Fscores": null,
        "T4 Fscores": null
    },
    {
        "Google Processor Name": "IL_Ver_B_Well_Completion",
        "OGRRE Document Type": "Well Completion Report Types B, C, D, E",
        "Page Order Sort": 107.0,
        "Name": "Gas_PSI",
        "Google Data type": "Plain text",
        "Occurrence": "Optional once",
        "Grouping": null,
        "Database Data Type": "float",
        "Cleaning Function": "string_to_float",
        "Accepted Range": null,
        "Field Specific Notes": null,
        "Model Enabled": "No",
        "V1 Fscores": null,
        "V2 Fscores": null,
        "V3 Fscores": null,
        "T1 Fscores": null,
        "T2 Fscores": null,
        "T3 Fscores": null,
        "T4 Fscores": null
    },
    {
        "Google Processor Name": "IL_Ver_B_Well_Completion",
        "OGRRE Document Type": "Well Completion Report Types B, C, D, E",
        "Page Order Sort": 108.0,
        "Name": "Signature_Of_Permittee_Or_Designee",
        "Google Data type": "Plain text",
        "Occurrence": "Optional once",
        "Grouping": null,
        "Database Data Type": "str",
        "Cleaning Function": null,
        "Accepted Range": "A-z0-9{1,60}",
        "Field Specific Notes": null,
        "Model Enabled": "No",
        "V1 Fscores": null,
        "V2 Fscores": null,
        "V3 Fscores": null,
        "T1 Fscores": null,
        "T2 Fscores": null,
        "T3 Fscores": null,
        "T4 Fscores": null
    },
    {
        "Google Processor Name": "IL_Ver_B_Well_Completion",
        "OGRRE Document Type": "Well Completion Report Types B, C, D, E",
        "Page Order Sort": 109.0,
        "Name": "Title",
        "Google Data type": "Plain text",
        "Occurrence": "Optional once",
        "Grouping": null,
        "Database Data Type": "str",
        "Cleaning Function": null,
        "Accepted Range": "A-z0-9{1,60}",
        "Field Specific Notes": null,
        "Model Enabled": "Yes",
        "V1 Fscores": 0.9,
        "V2 Fscores": 0.908,
        "V3 Fscores": 0.924,
        "T1 Fscores": 0.818,
        "T2 Fscores": 0.948,
        "T3 Fscores": 0.938,
        "T4 Fscores": 0.956
    },
    {
        "Google Processor Name": "IL_Ver_B_Well_Completion",
        "OGRRE Document Type": "Well Completion Report Types B, C, D, E",
        "Page Order Sort": 110.0,
        "Name": "Address",
        "Google Data type": "Plain text",
        "Occurrence": "Optional once",
        "Grouping": null,
        "Database Data Type": "str",
        "Cleaning Function": null,
        "Accepted Range": "A-z0-9{1,60}",
        "Field Specific Notes": null,
        "Model Enabled": "Yes",
        "V1 Fscores": 0.857,
        "V2 Fscores": 0.875,
        "V3 Fscores": 0.868,
        "T1 Fscores": 0.597,
        "T2 Fscores": 0.803,
        "T3 Fscores": 0.92,
        "T4 Fscores": 0.911
    },
    {
        "Google Processor Name": "IL_Ver_B_Well_Completion",
        "OGRRE Document Type": "Well Completion Report Types B, C, D, E",
        "Page Order Sort": 111.0,
        "Name": "Date_Signed",
        "Google Data type": "Datetime",
        "Occurrence": "Optional once",
        "Grouping": null,
        "Database Data Type": "date",
        "Cleaning Function": "clean_date",
        "Accepted Range": null,
        "Field Specific Notes": null,
        "Model Enabled": "Yes",
        "V1 Fscores": 0.969,
        "V2 Fscores": 0.981,
        "V3 Fscores": 0.981,
        "T1 Fscores": 0.809,
        "T2 Fscores": 0.975,
        "T3 Fscores": 0.963,
        "T4 Fscores": 0.963
    },
    {
        "Google Processor Name": "IL_Ver_B_Well_Completion",
        "OGRRE Document Type": "Well Completion Report Types B, C, D, E",
        "Page Order Sort": 112.0,
        "Name": "City_State",
        "Google Data type": "Plain text",
        "Occurrence": "Optional once",
        "Grouping": null,
        "Database Data Type": "str",
        "Cleaning Function": null,
        "Accepted Range": "A-z0-9{1,60}",
        "Field Specific Notes": null,
        "Model Enabled": "Yes",
        "V1 Fscores": 0.909,
        "V2 Fscores": 0.909,
        "V3 Fscores": 0.897,
        "T1 Fscores": 0.672,
        "T2 Fscores": 0.928,
        "T3 Fscores": 0.956,
        "T4 Fscores": 0.943
    },
    {
        "Google Processor Name": null,
        "OGRRE Document Type": null,
        "Page Order Sort": null,
        "Name": "Packer_Brand_And_Type",
        "Google Data type": "Plain text",
        "Occurrence": "Optional multiple",
        "Grouping": null,
        "Database Data Type": "str",
        "Cleaning Function": null,
        "Accepted Range": "A-z0-9{1,20}",
        "Field Specific Notes": "{#, TD, Total Depth}, #==Float, TD and Total Depth ==Total_Depth",
        "Model Enabled": "No",
        "V1 Fscores": null,
        "V2 Fscores": null,
        "V3 Fscores": 0.564,
        "T1 Fscores": null,
        "T2 Fscores": null,
        "T3 Fscores": 0.873,
        "T4 Fscores": 0.94
    },
    {
        "Google Processor Name": null,
        "OGRRE Document Type": null,
        "Page Order Sort": null,
        "Name": "Packer_Setting_Depth",
        "Google Data type": "Plain text",
        "Occurrence": "Optional multiple",
        "Grouping": null,
        "Database Data Type": "float",
        "Cleaning Function": "string_to_float",
        "Accepted Range": null,
        "Field Specific Notes": "{#, TD, Total Depth}, #==Float, TD and Total Depth ==Total_Depth",
        "Model Enabled": "No",
        "V1 Fscores": null,
        "V2 Fscores": null,
        "V3 Fscores": 0.645,
        "T1 Fscores": null,
        "T2 Fscores": null,
        "T3 Fscores": 1.0,
        "T4 Fscores": 1.0
    },
    {
        "Google Processor Name": null,
        "OGRRE Document Type": null,
        "Page Order Sort": null,
        "Name": "Type_Of_Log",
        "Google Data type": "Plain text",
        "Occurrence": "Optional multiple",
        "Grouping": null,
        "Database Data Type": "str",
        "Cleaning Function": null,
        "Accepted Range": "A-z0-9{1,60}",
        "Field Specific Notes": null,
        "Model Enabled": "No",
        "V1 Fscores": 0.842,
        "V2 Fscores": 0.822,
        "V3 Fscores": null,
        "T1 Fscores": 0.943,
        "T2 Fscores": 0.864,
        "T3 Fscores": null,
        "T4 Fscores": null
    },
    {
        "Google Processor Name": null,
        "OGRRE Document Type": null,
        "Page Order Sort": null,
        "Name": "Type_Of_Log_Date",
        "Google Data type": "Datetime",
        "Occurrence": "Optional multiple",
        "Grouping": null,
        "Database Data Type": "date",
        "Cleaning Function": "clean_date",
        "Accepted Range": null,
        "Field Specific Notes": null,
        "Model Enabled": "No",
        "V1 Fscores": 0.972,
        "V2 Fscores": 0.989,
        "V3 Fscores": null,
        "T1 Fscores": 0.973,
        "T2 Fscores": 0.973,
        "T3 Fscores": null,
        "T4 Fscores": null
    }
]